eidolon_browser_service/__init__.py
eidolon_browser_service/api.py
eidolon_browser_service/async_client.py
eidolon_browser_service/browser.py
eidolon_browser_service/browser_logging.py
eidolon_browser_service/main.py
eidolon_browser_service/service.py
eidolon_browser_service-0.1.7.dist-info/METADATA
eidolon_browser_service-0.1.7.dist-info/WHEEL
eidolon_browser_service-0.1.7.dist-info/RECORD
