Metadata-Version: 2.1
Name: eidolon-browser-service
Version: 0.1.7
Summary: Lightweight playwright wrapper for AI Agents
Author: Luke Lalor
Author-email: lukehlalor@gmail.com
Requires-Python: >=3.10,<3.13
Classifier: Programming Language :: Python :: 3
Classifier: Programming Language :: Python :: 3.10
Classifier: Programming Language :: Python :: 3.11
Classifier: Programming Language :: Python :: 3.12
Provides-Extra: server
Requires-Dist: fastapi[standard] (>=0.115.6,<0.116.0) ; extra == "server"
Requires-Dist: playwright (>=1.49.0,<2.0.0) ; extra == "server"
Requires-Dist: pydantic (>=2.10.3,<3.0.0)
Project-URL: Github, https://github.com/eidolon-ai/eidolon
Project-URL: Website, https://www.eidolonai.com/
